flake8_mypy.py
flake8_mypy-17.3.3.dist-info/DESCRIPTION.rst
flake8_mypy-17.3.3.dist-info/METADATA
flake8_mypy-17.3.3.dist-info/RECORD
flake8_mypy-17.3.3.dist-info/WHEEL
flake8_mypy-17.3.3.dist-info/entry_points.txt
flake8_mypy-17.3.3.dist-info/metadata.json
flake8_mypy-17.3.3.dist-info/top_level.txt
