Metadata-Version: 2.0
Name: flake8-mypy
Version: 17.3.3
Summary: A plugin for flake8 integrating mypy.
Home-page: https://github.com/ambv/flake8-mypy
Author: Łukasz Langa
Author-email: lukasz@langa.pl
License: MIT
Keywords: flake8 mypy bugs linter qa typing
Platform: UNKNOWN
Classifier: Development Status :: 3 - Alpha
Classifier: Environment :: Console
Classifier: Framework :: Flake8
Classifier: Intended Audience :: Developers
Classifier: License :: OSI Approved :: MIT License
Classifier: Operating System :: OS Independent
Classifier: Programming Language :: Python
Classifier: Programming Language :: Python :: 3.5
Classifier: Programming Language :: Python :: 3.6
Classifier: Topic :: Software Development :: Libraries :: Python Modules
Classifier: Topic :: Software Development :: Quality Assurance
Requires-Dist: attrs
Requires-Dist: flake8 (>=3.0.0)
Requires-Dist: mypy
